[{"City":"San Diego"," State":" CA"," CPI": 269.44},
  {"City":"New York"," State":" NY"," CPI": 260.56},
  {"City":"New Jersey"," State":" NJ"," CPI": 260.56},
  {"City":"Long Island"," State":" NY"," CPI": 260.56},
  {"City":"San Francisco"," State":" CA"," CPI": 258.57},
  {"City":"Oakland"," State":" CA"," CPI": 258.57},
  {"City":"San Jose"," State":" CA"," CPI": 258.57},
  {"City":"Boston"," State":" MA"," CPI": 256.72},
  {"City":"Brockton"," State":" MA"," CPI": 256.72},
  {"City":"Nashua"," State":" NH"," CPI": 256.72},
  {"City":"Seattle"," State":" WA"," CPI": 249.36},
  {"City":"Tacoma"," State":" WA"," CPI": 249.36},
  {"City":"Miami"," State":" FL"," CPI": 245.42},
  {"City":"Fort Lauderdale"," State":" FL"," CPI": 245.42}]